p5/diferencia.vhd
library IEEE;
use IEEE.STD_LOGIC_1164.ALL;
use IEEE.numeric_std.all;


entity diferencia is
  Port ( 
    clk, reset : in std_logic;
    Y, Z : in unsigned(7 downto 0);
    valY, valZ : in std_logic;    
    res, vRes : out std_logic
    );
end diferencia;

architecture rtl of diferencia is
 
    signal regY, regZ : unsigned(7 downto 0);
    signal regValido : std_logic;
    
signal dif, abso : signed(8 downto 0);
signal uY, uZ : unsigned(8 downto 0);
-- nota: dif, abso, uY y uZ podrían ser variables en el proceso "calculos"
--       pero entonces no serían visibles durante la simulación
--       y sería más complicado depurar los posibles errores

    
begin


vRes <= regValido; 	-- se puede poner fuera del proceso

calculos:process(regY, regZ, regValido, uZ, uY, regY, regZ, dif, abso)	-- lista de sensibilidad exhaustiva
begin
   
    
    uY <= "0" & regY;					-- extensión a 9 bits
    uZ <= "0" & regZ;
    
    dif <= signed(uY) - signed(uZ);		-- resta con signo
    
	-- (1) calcular aquí "abso" a partir de "dif"
	if dif < 0 then
    		abso <= 0-dif;
	else
		abso <= dif;
	end if;
	
    -- (2) res = 1 si abso < 6, y cero en caso contrario
	if abso < 6 then
		res <= '1';
	else 
		res <= '0';
	end if;
	vRes <= '1';

end process;

    
sync:process(clk, reset, Y, Z, valZ, valY)
begin

  if rising_edge( clk ) then
    if reset = '1' then
      regZ <= x"00";
      regY <= x"00";
      regValido <= '0';
    else
	
      -- (3) registra aquí las entradas del circuito
	  
      regZ <= Z;
      regY <= Y;
      regValido <= valY and valZ;
    end if;
  end if;

end process;    


end rtl;

p5/duplicar.vhd
library IEEE;
use IEEE.STD_LOGIC_1164.ALL;
use IEEE.numeric_std.all;


entity duplicar is
  Port ( 
    clk, reset : in std_logic;
    X : in unsigned(7 downto 0);
    valX : in std_logic;    
    Y, Z : out unsigned(7 downto 0);
    valY, valZ : out std_logic
    );
end duplicar;

architecture rtl of duplicar is
 
    signal a, b, c : unsigned(7 downto 0);
    signal valido : std_logic;
begin

replicar:process(a, c, valido)
begin

    Y <= a; 
    Z <= c;
    valY <= valido;
    valZ <= valido;
    
end process;
    
    
sync:process(clk, reset, X, valX, a, b, c, valido)
begin

  if rising_edge( clk ) then
    if reset = '1' then
      a <= x"00";
      b <= x"00";
      c <= x"00";
      valido <= '0';
    else
      c <= b;
      b <= a;
      a <= X;
      valido <= valX;
    end if;
  end if;

end process;    


end rtl;

p5/practica_2_2.vhd
library IEEE;
use IEEE.STD_LOGIC_1164.ALL;
use IEEE.numeric_std.all;


entity practica_2_2 is
  Port ( 
    clk, reset : in std_logic;
    X : in unsigned(7 downto 0);
    valX : in std_logic;    
    res, vRes : out std_logic
    );
end practica_2_2;


architecture rtl of practica_2_2 is
 
    signal qY, qZ : unsigned(7 downto 0);
    signal vY, vZ : std_logic;
    
    component duplicar
        Port ( 
        clk, reset : in std_logic;
        X : in unsigned(7 downto 0);
        valX : in std_logic;    
        Y, Z : out unsigned(7 downto 0);
        valY, valZ : out std_logic
        ); 
    end component;        
        
    component diferencia
        Port ( 
        clk, reset : in std_logic;
        Y, Z : in unsigned(7 downto 0);
        valY, valZ : in std_logic;    
        res, vRes : out std_logic
        );            
    end component;            
        
begin
   
   instDup:duplicar port map(  clk => clk, reset => reset, X => X, valX => valX, Y => qY, Z => qZ, valY => vY, valZ => vZ);
   
   instDif:diferencia port map(  clk => clk, reset => reset, Z => qZ, valZ => vZ, Y => qY, valY => vY, res => res, vRes => vRes);
   
   
   
end rtl;

p5/TB_practica_2_2.vhd
library IEEE;
use IEEE.STD_LOGIC_1164.ALL;
USE ieee.numeric_std.ALL;
use IEEE.std_logic_textio.all;
use std.textio.all;



entity TB_practica_2_2 is

end TB_practica_2_2;

architecture Behavioral of TB_practica_2_2 is

	component practica_2_2 port (
    clk, reset : in std_logic;
    X : in unsigned(7 downto 0);
    valX : in std_logic;    
    res, vRes : out std_logic);
	end component;

signal X : unsigned(7 downto 0);            -- señales para conectar   
signal valX, res, vRes : std_logic;
signal dummy1, dummy2, dummy3, check : std_logic_vector(0 downto 0);
signal clk : std_logic := '0';
signal reset : std_logic := '1';

begin

	instancia: practica_2_2 port map(       -- instancia aquí la ALU, conectando todos sus puertos
	    clk, reset, X, valX, res, vRes
		);

	reloj: process
		variable i : integer;
	begin
		for i in 1 to 7020 loop
			clk <= not clk;
			wait for 0.5 ns;
		end loop;
		wait;
	end process;

	-- creando el reset
	ini: process
	begin
		reset<='1';
		wait until clk'event and clk='1';
		reset<='0' after 2 ns;
		wait;
	end process;	
	


	simulacion: process	
	file stimul_io : text is in "./practica_2_2_IN.txt";
	variable aline, oline: line;	
	variable i_X, i_valX  : integer; 
	variable o_res, o_vRes : integer;
	variable C_res, C_vRes : integer;  
	variable dummyA, dummyB, dummyC : std_logic_vector(0 downto 0);
	
	begin
	
		wait until reset'event and reset = '0';
	
		loop
		
			wait until clk'event and clk = '1';
		    wait for 0 ns;
			
			if (not(endfile(stimul_io))) then
				readline(stimul_io, aline);
				read(aline, i_X);
				read(aline, i_valX);
				read(aline, o_res);       
                read(aline, o_vRes);  

			else
				assert false
					report "Se ha llegado al final del fichero de entrada. Comprobar si hay errores anteriores a este mensaje."
					severity failure;
					file_close(stimul_io);
			end if;



			X <= to_unsigned(i_X, 8);
			dummyA := std_logic_vector(to_unsigned(i_valX, 1));						
			valX <= dummyA(0);
			dummyB := std_logic_vector(to_unsigned(o_res, 1));						
			dummyC := std_logic_vector(to_unsigned(o_vRes, 1));	
			
			check <= dummyB;
			
            wait for 500 ps;
            
            dummy2(0) <= res;
            dummy3(0) <= vRes;  
			C_res := to_integer(unsigned(dummy2));
			C_vRes := to_integer(unsigned(dummy3));

			
			assert (C_res = o_res)  -- debe coincidir con el valor leido del fichero
				report "No coincide el valor de res " & integer'image(C_res) & "  " & integer'image(o_res)				
				severity error;						

			assert (C_vRes = o_vRes)  -- debe coincidir con el valor leido del fichero
				report "No coincide el valor de validez "  & integer'image(C_vRes) & "  " & integer'image(o_vRes)				
				severity error;		

		end loop;
	end process;



end Behavioral;

p5/resultados.vcd
$date
  Tue Apr 27 15:20:27 2021
$end
$version
  GHDL v0
$end
$timescale
  1 fs
$end
$scope module standard $end
$upscope $end
$scope module std_logic_1164 $end
$upscope $end
$scope module numeric_std $end
$upscope $end
$scope module textio $end
$upscope $end
$scope module std_logic_textio $end
$upscope $end
$scope module tb_practica_2_2 $end
$var reg 8 ! x[7:0] $end
$var reg 1 " valx $end
$var reg 1 # res $end
$var reg 1 $ vres $end
$var reg 1 % dummy1[0:0] $end
$var reg 1 & dummy2[0:0] $end
$var reg 1 ' dummy3[0:0] $end
$var reg 1 ( check[0:0] $end
$var reg 1 ) clk $end
$var reg 1 * reset $end
$scope module instancia $end
$var reg 1 + clk $end
$var reg 1 , reset $end
$var reg 8 - x[7:0] $end
$var reg 1 . valx $end
$var reg 1 / res $end
$var reg 1 0 vres $end
$var reg 8 1 qy[7:0] $end
$var reg 8 2 qz[7:0] $end
$var reg 1 3 vy $end
$var reg 1 4 vz $end
$scope module instdup $end
$var reg 1 5 clk $end
$var reg 1 6 reset $end
$var reg 8 7 x[7:0] $end
$var reg 1 8 valx $end
$var reg 8 9 y[7:0] $end
$var reg 8 : z[7:0] $end
$var reg 1 ; valy $end
$var reg 1 < valz $end
$var reg 8 = a[7:0] $end
$var reg 8 > b[7:0] $end
$var reg 8 ? c[7:0] $end
$var reg 1 @ valido $end
$upscope $end
$scope module instdif $end
$var reg 1 A clk $end
$var reg 1 B reset $end
$var reg 8 C y[7:0] $end
$var reg 8 D z[7:0] $end
$var reg 1 E valy $end
$var reg 1 F valz $end
$var reg 1 G res $end
$var reg 1 H vres $end
$var reg 8 I regy[7:0] $end
$var reg 8 J regz[7:0] $end
$var reg 1 K regvalido $end
$var reg 9 L dif[8:0] $end
$var reg 9 M abso[8:0] $end
$var reg 9 N uy[8:0] $end
$var reg 9 O uz[8:0] $end
$upscope $end
$upscope $end
$upscope $end
$enddefinitions $end
#0
bUUUUUUUU !
U"
1#
X$
bU %
bU &
bU '
bU (
1)
1*
1+
1,
bUUUUUUUU -
U.
1/
X0
b00000000 1
b00000000 2
03
04
15
16
bUUUUUUUU 7
U8
b00000000 9
b00000000 :
0;
0<
b00000000 =
b00000000 >
b00000000 ?
0@
1A
1B
b00000000 C
b00000000 D
0E
0F
1G
XH
b00000000 I
b00000000 J
0K
b000000000 L
b000000000 M
b000000000 N
b000000000 O
#500000
0)
0+
05
0A
#1000000
1)
1+
15
1A
#1500000
0)
0+
05
0A
#2000000
b00000001 !
1"
b0 (
1)
0*
1+
0,
b00000001 -
1.
bUUUUUUUU 1
U3
U4
15
06
b00000001 7
18
bUUUUUUUU 9
U;
U<
bUUUUUUUU =
U@
1A
0B
bUUUUUUUU C
UE
UF
#2500000
b1 &
bX '
0)
0+
05
0A
#3000000
b00001010 !
0#
U$
b1 (
1)
1+
b00001010 -
0/
U0
b00000001 1
13
14
15
b00001010 7
b00000001 9
1;
1<
b00000001 =
bUUUUUUUU >
1@
1A
b00000001 C
1E
1F
0G
UH
bUUUUUUUU I
UK
bXXXXXXXXX L
bXXXXXXXXX M
b0UUUUUUUU N
#3500000
b0 &
bU '
0)
0+
05
0A
#4000000
b00000111 !
1#
1$
b0 (
1)
1+
b00000111 -
1/
10
b00001010 1
bUUUUUUUU 2
15
b00000111 7
b00001010 9
bUUUUUUUU :
b00001010 =
b00000001 >
bUUUUUUUU ?
1A
b00001010 C
bUUUUUUUU D
1G
1H
b00000001 I
1K
b000000001 L
b000000001 M
b000000001 N
#4500000
b1 &
b1 '
0)
0+
05
0A
#5000000
b00000000 !
0#
b1 (
1)
1+
b00000000 -
0/
10
b00000111 1
b00000001 2
15
b00000000 7
b00000111 9
b00000001 :
b00000111 =
b00001010 >
b00000001 ?
1A
b00000111 C
b00000001 D
0G
1H
b00001010 I
bUUUUUUUU J
bXXXXXXXXX L
bXXXXXXXXX M
b000001010 N
b0UUUUUUUU O
#5500000
b0 &
0)
0+
05
0A
#6000000
b0 (
1)
1+
10
b00000000 1
b00001010 2
15
b00000000 9
b00001010 :
b00000000 =
b00000111 >
b00001010 ?
1A
b00000000 C
b00001010 D
1H
b00000111 I
b00000001 J
b000000110 L
b000000110 M
b000000111 N
b000000001 O
#6500000
0)
0+
05
0A
#7000000
1)
1+
10
b00000111 2
15
b00000111 :
b00000000 >
b00000111 ?
1A
b00000111 D
1H
b00000000 I
b00001010 J
b111110110 L
b000001010 M
b000000000 N
b000001010 O
#7500000
0)
0+
05
0A
#8000000
b00001101 !
1)
1+
b00001101 -
10
b00000000 2
15
b00001101 7
b00000000 :
b00000000 ?
1A
b00000000 D
1H
b00000111 J
b111111001 L
b000000111 M
b000000111 O
#8500000
0)
0+
05
0A
#9000000
b01000100 !
1#
1)
1+
b01000100 -
1/
10
b00001101 1
15
b01000100 7
b00001101 9
b00001101 =
1A
b00001101 C
1G
1H
b00000000 J
b000000000 L
b000000000 M
b000000000 O
#9500000
b1 &
0)
0+
05
0A
#10000000
b01010010 !
0#
b1 (
1)
1+
b01010010 -
0/
10
b01000100 1
15
b01010010 7
b01000100 9
b01000100 =
b00001101 >
1A
b01000100 C
0G
1H
b00001101 I
b000001101 L
b000001101 M
b000001101 N
#10500000
b0 &
0)
0+
05
0A
#11000000
b01010100 !
b0 (
1)
1+
b01010100 -
10
b01010010 1
b00001101 2
15
b01010100 7
b01010010 9
b00001101 :
b01010010 =
b01000100 >
b00001101 ?
1A
b01010010 C
b00001101 D
1H
b01000100 I
b001000100 L
b001000100 M
b001000100 N
#11500000
0)
0+
05
0A
#12000000
b01010010 !
1)
1+
b01010010 -
10
b01010100 1
b01000100 2
15
b01010010 7
b01010100 9
b01000100 :
b01010100 =
b01010010 >
b01000100 ?
1A
b01010100 C
b01000100 D
1H
b01010010 I
b00001101 J
b001000101 L
b001000101 M
b001010010 N
b000001101 O
#12500000
0)
0+
05
0A
#13000000
b01010001 !
1)
1+
b01010001 -
10
b01010010 1
b01010010 2
15
b01010001 7
b01010010 9
b01010010 :
b01010010 =
b01010100 >
b01010010 ?
1A
b01010010 C
b01010010 D
1H
b01010100 I
b01000100 J
b000010000 L
b000010000 M
b001010100 N
b001000100 O
#13500000
0)
0+
05
0A
#14000000
b01001101 !
1#
1)
1+
b01001101 -
1/
10
b01010001 1
b01010100 2
15
b01001101 7
b01010001 9
b01010100 :
b01010001 =
b01010010 >
b01010100 ?
1A
b01010001 C
b01010100 D
1G
1H
b01010010 I
b01010010 J
b000000000 L
b000000000 M
b001010010 N
b001010010 O
#14500000
b1 &
0)
0+
05
0A
#15000000
b01001000 !
b1 (
1)
1+
b01001000 -
10
b01001101 1
b01010010 2
15
b01001000 7
b01001101 9
b01010010 :
b01001101 =
b01010001 >
b01010010 ?
1A
b01001101 C
b01010010 D
1H
b01010001 I
b01010100 J
b111111101 L
b000000011 M
b001010001 N
b001010100 O
#15500000
0)
0+
05
0A
#16000000
b01001010 !
1)
1+
b01001010 -
10
b01001000 1
b01010001 2
15
b01001010 7
b01001000 9
b01010001 :
b01001000 =
b01001101 >
b01010001 ?
1A
b01001000 C
b01010001 D
1H
b01001101 I
b01010010 J
b111111011 L
b000000101 M
b001001101 N
b001010010 O
#16500000
0)
0+
05
0A
#17000000
b01001011 !
0#
1)
1+
b01001011 -
0/
10
b01001010 1
b01001101 2
15
b01001011 7
b01001010 9
b01001101 :
b01001010 =
b01001000 >
b01001101 ?
1A
b01001010 C
b01001101 D
0G
1H
b01001000 I
b01010001 J
b111110111 L
b000001001 M
b001001000 N
b001010001 O
#17500000
b0 &
0)
0+
05
0A
#18000000
b01001010 !
1#
b0 (
1)
1+
b01001010 -
1/
10
b01001011 1
b01001000 2
15
b01001010 7
b01001011 9
b01001000 :
b01001011 =
b01001010 >
b01001000 ?
1A
b01001011 C
b01001000 D
1G
1H
b01001010 I
b01001101 J
b111111101 L
b000000011 M
b001001010 N
b001001101 O
#18500000
b1 &
0)
0+
05
0A
#19000000
b01001011 !
b1 (
1)
1+
b01001011 -
10
b01001010 1
b01001010 2
15
b01001011 7
b01001010 9
b01001010 :
b01001010 =
b01001011 >
b01001010 ?
1A
b01001010 C
b01001010 D
1H
b01001011 I
b01001000 J
b000000011 L
b001001011 N
b001001000 O
#19500000
0)
0+
05
0A
#20000000
b01000101 !
1)
1+
b01000101 -
10
b01001011 1
b01001011 2
15
b01000101 7
b01001011 9
b01001011 :
b01001011 =
b01001010 >
b01001011 ?
1A
b01001011 C
b01001011 D
1H
b01001010 I
b01001010 J
b000000000 L
b000000000 M
b001001010 N
b001001010 O
#20500000
0)
0+
05
0A
#21000000
b00111111 !
1)
1+
b00111111 -
10
b01000101 1
b01001010 2
15
b00111111 7
b01000101 9
b01001010 :
b01000101 =
b01001011 >
b01001010 ?
1A
b01000101 C
b01001010 D
1H
b01001011 I
b01001011 J
b001001011 N
b001001011 O
#21500000
0)
0+
05
0A
#22000000
b00111000 !
1)
1+
b00111000 -
10
b00111111 1
b01001011 2
15
b00111000 7
b00111111 9
b01001011 :
b00111111 =
b01000101 >
b01001011 ?
1A
b00111111 C
b01001011 D
1H
b01000101 I
b01001010 J
b111111011 L
b000000101 M
b001000101 N
b001001010 O
#22500000
0)
0+
05
0A
#23000000
b00111001 !
0#
1)
1+
b00111001 -
0/
10
b00111000 1
b01000101 2
15
b00111001 7
b00111000 9
b01000101 :
b00111000 =
b00111111 >
b01000101 ?
1A
b00111000 C
b01000101 D
0G
1H
b00111111 I
b01001011 J
b111110100 L
b000001100 M
b000111111 N
b001001011 O
#23500000
b0 &
0)
0+
05
0A
#24000000
b00111011 !
b0 (
1)
1+
b00111011 -
10
b00111001 1
b00111111 2
15
b00111011 7
b00111001 9
b00111111 :
b00111001 =
b00111000 >
b00111111 ?
1A
b00111001 C
b00111111 D
1H
b00111000 I
b01000101 J
b111110011 L
b000001101 M
b000111000 N
b001000101 O
#24500000
0)
0+
05
0A
#25000000
b00111001 !
1)
1+
b00111001 -
10
b00111011 1
b00111000 2
15
b00111001 7
b00111011 9
b00111000 :
b00111011 =
b00111001 >
b00111000 ?
1A
b00111011 C
b00111000 D
1H
b00111001 I
b00111111 J
b111111010 L
b000000110 M
b000111001 N
b000111111 O
#25500000
0)
0+
05
0A
#26000000
b00111011 !
1#
1)
1+
b00111011 -
1/
10
b00111001 1
b00111001 2
15
b00111011 7
b00111001 9
b00111001 :
b00111001 =
b00111011 >
b00111001 ?
1A
b00111001 C
b00111001 D
1G
1H
b00111011 I
b00111000 J
b000000011 L
b000000011 M
b000111011 N
b000111000 O
#26500000
b1 &
0)
0+
05
0A
#27000000
b01000110 !
b1 (
1)
1+
b01000110 -
10
b00111011 1
b00111011 2
15
b01000110 7
b00111011 9
b00111011 :
b00111011 =
b00111001 >
b00111011 ?
1A
b00111011 C
b00111011 D
1H
b00111001 I
b00111001 J
b000000000 L
b000000000 M
b000111001 N
b000111001 O
#27500000
0)
0+
05
0A
#28000000
b01010000 !
1)
1+
b01010000 -
10
b01000110 1
b00111001 2
15
b01010000 7
b01000110 9
b00111001 :
b01000110 =
b00111011 >
b00111001 ?
1A
b01000110 C
b00111001 D
1H
b00111011 I
b00111011 J
b000111011 N
b000111011 O
#28500000
0)
0+
05
0A
#29000000
b01010101 !
0#
1)
1+
b01010101 -
0/
10
b01010000 1
b00111011 2
15
b01010101 7
b01010000 9
b00111011 :
b01010000 =
b01000110 >
b00111011 ?
1A
b01010000 C
b00111011 D
0G
1H
b01000110 I
b00111001 J
b000001101 L
b000001101 M
b001000110 N
b000111001 O
#29500000
b0 &
0)
0+
05
0A
#30000000
b01010011 !
b0 (
1)
1+
b01010011 -
10
b01010101 1
b01000110 2
15
b01010011 7
b01010101 9
b01000110 :
b01010101 =
b01010000 >
b01000110 ?
1A
b01010101 C
b01000110 D
1H
b01010000 I
b00111011 J
b000010101 L
b000010101 M
b001010000 N
b000111011 O
#30500000
0)
0+
05
0A
#31000000
b01010100 !
1)
1+
b01010100 -
10
b01010011 1
b01010000 2
15
b01010100 7
b01010011 9
b01010000 :
b01010011 =
b01010101 >
b01010000 ?
1A
b01010011 C
b01010000 D
1H
b01010101 I
b01000110 J
b000001111 L
b000001111 M
b001010101 N
b001000110 O
#31500000
0)
0+
05
0A
#32000000
b01010101 !
1#
1)
1+
b01010101 -
1/
10
b01010100 1
b01010101 2
15
b01010101 7
b01010100 9
b01010101 :
b01010100 =
b01010011 >
b01010101 ?
1A
b01010100 C
b01010101 D
1G
1H
b01010011 I
b01010000 J
b000000011 L
b000000011 M
b001010011 N
b001010000 O
#32500000
b1 &
0)
0+
05
0A
#33000000
b01010100 !
b1 (
1)
1+
b01010100 -
10
b01010101 1
b01010011 2
15
b01010100 7
b01010101 9
b01010011 :
b01010101 =
b01010100 >
b01010011 ?
1A
b01010101 C
b01010011 D
1H
b01010100 I
b01010101 J
b111111111 L
b000000001 M
b001010100 N
b001010101 O
#33500000
0)
0+
05
0A
#34000000
b01010101 !
1)
1+
b01010101 -
10
b01010100 1
b01010100 2
15
b01010101 7
b01010100 9
b01010100 :
b01010100 =
b01010101 >
b01010100 ?
1A
b01010100 C
b01010100 D
1H
b01010101 I
b01010011 J
b000000010 L
b000000010 M
b001010101 N
b001010011 O
#34500000
0)
0+
05
0A
#35000000
b01010100 !
1)
1+
b01010100 -
10
b01010101 1
b01010101 2
15
b01010100 7
b01010101 9
b01010101 :
b01010101 =
b01010100 >
b01010101 ?
1A
b01010101 C
b01010101 D
1H
b01010100 I
b01010100 J
b000000000 L
b000000000 M
b001010100 N
b001010100 O
#35500000
0)
0+
05
0A
#36000000
b01010000 !
1)
1+
b01010000 -
10
b01010100 1
b01010100 2
15
b01010000 7
b01010100 9
b01010100 :
b01010100 =
b01010101 >
b01010100 ?
1A
b01010100 C
b01010100 D
1H
b01010101 I
b01010101 J
b001010101 N
b001010101 O
#36500000
0)
0+
05
0A
#37000000
b01001010 !
1)
1+
b01001010 -
10
b01010000 1
b01010101 2
15
b01001010 7
b01010000 9
b01010101 :
b01010000 =
b01010100 >
b01010101 ?
1A
b01010000 C
b01010101 D
1H
b01010100 I
b01010100 J
b001010100 N
b001010100 O
#37500000
0)
0+
05
0A
#38000000
b01001000 !
1)
1+
b01001000 -
10
b01001010 1
b01010100 2
15
b01001000 7
b01001010 9
b01010100 :
b01001010 =
b01010000 >
b01010100 ?
1A
b01001010 C
b01010100 D
1H
b01010000 I
b01010101 J
b111111011 L
b000000101 M
b001010000 N
b001010101 O
#38500000
0)
0+
05
0A
#39000000
b01001011 !
0#
1)
1+
b01001011 -
0/
10
b01001000 1
b01010000 2
15
b01001011 7
b01001000 9
b01010000 :
b01001000 =
b01001010 >
b01010000 ?
1A
b01001000 C
b01010000 D
0G
1H
b01001010 I
b01010100 J
b111110110 L
b000001010 M
b001001010 N
b001010100 O
#39500000
b0 &
0)
0+
05
0A
#40000000
b01010000 !
b0 (
1)
1+
b01010000 -
10
b01001011 1
b01001010 2
15
b01010000 7
b01001011 9
b01001010 :
b01001011 =
b01001000 >
b01001010 ?
1A
b01001011 C
b01001010 D
1H
b01001000 I
b01010000 J
b111111000 L
b000001000 M
b001001000 N
b001010000 O
#40500000
0)
0+
05
0A
#41000000
b01010110 !
1#
1)
1+
b01010110 -
1/
10
b01010000 1
b01001000 2
15
b01010110 7
b01010000 9
b01001000 :
b01010000 =
b01001011 >
b01001000 ?
1A
b01010000 C
b01001000 D
1G
1H
b01001011 I
b01001010 J
b000000001 L
b000000001 M
b001001011 N
b001001010 O
#41500000
b1 &
0)
0+
05
0A
#42000000
0#
b1 (
1)
1+
0/
10
b01010110 1
b01001011 2
15
b01010110 9
b01001011 :
b01010110 =
b01010000 >
b01001011 ?
1A
b01010110 C
b01001011 D
0G
1H
b01010000 I
b01001000 J
b000001000 L
b000001000 M
b001010000 N
b001001000 O
#42500000
b0 &
0)
0+
05
0A
#43000000
b01010111 !
b0 (
1)
1+
b01010111 -
10
b01010000 2
15
b01010111 7
b01010000 :
b01010110 >
b01010000 ?
1A
b01010000 D
1H
b01010110 I
b01001011 J
b000001011 L
b000001011 M
b001010110 N
b001001011 O
#43500000
0)
0+
05
0A
#44000000
1)
1+
10
b01010111 1
b01010110 2
15
b01010111 9
b01010110 :
b01010111 =
b01010110 ?
1A
b01010111 C
b01010110 D
1H
b01010000 J
b000000110 L
b000000110 M
b001010000 O
#44500000
0)
0+
05
0A
#45000000
b01011001 !
1#
1)
1+
b01011001 -
1/
10
15
b01011001 7
b01010111 >
1A
1G
1H
b01010111 I
b01010110 J
b000000001 L
b000000001 M
b001010111 N
b001010110 O
#45500000
b1 &
0)
0+
05
0A
#46000000
b01011100 !
b1 (
1)
1+
b01011100 -
b01011001 1
b01010111 2
15
b01011100 7
b01011001 9
b01010111 :
b01011001 =
b01010111 ?
1A
b01011001 C
b01010111 D
#46500000
0)
0+
05
0A
#47000000
b01011101 !
1)
1+
b01011101 -
10
b01011100 1
15
b01011101 7
b01011100 9
b01011100 =
b01011001 >
1A
b01011100 C
1H
b01011001 I
b01010111 J
b000000010 L
b000000010 M
b001011001 N
b001010111 O
#47500000
0)
0+
05
0A
#48000000
1)
1+
10
b01011101 1
b01011001 2
15
b01011101 9
b01011001 :
b01011101 =
b01011100 >
b01011001 ?
1A
b01011101 C
b01011001 D
1H
b01011100 I
b000000101 L
b000000101 M
b001011100 N
#48500000
0)
0+
05
0A
#49000000
b01011110 !
1)
1+
b01011110 -
10
b01011100 2
15
b01011110 7
b01011100 :
b01011101 >
b01011100 ?
1A
b01011100 D
1H
b01011101 I
b01011001 J
b000000100 L
b000000100 M
b001011101 N
b001011001 O
#49500000
0)
0+
05
0A
#50000000
b01011100 !
1)
1+
b01011100 -
10
b01011110 1
b01011101 2
15
b01011100 7
b01011110 9
b01011101 :
b01011110 =
b01011101 ?
1A
b01011110 C
b01011101 D
1H
b01011100 J
b000000001 L
b000000001 M
b001011100 O
#50500000
0)
0+
05
0A
#51000000
b01011011 !
1)
1+
b01011011 -
10
b01011100 1
15
b01011011 7
b01011100 9
b01011100 =
b01011110 >
1A
b01011100 C
1H
b01011110 I
b01011101 J
b001011110 N
b001011101 O
#51500000
0)
0+
05
0A
#52000000
b01011110 !
1)
1+
b01011110 -
10
b01011011 1
b01011110 2
15
b01011110 7
b01011011 9
b01011110 :
b01011011 =
b01011100 >
b01011110 ?
1A
b01011011 C
b01011110 D
1H
b01011100 I
b111111111 L
b001011100 N
#52500000
0)
0+
05
0A
#53000000
b01011111 !
1)
1+
b01011111 -
10
b01011110 1
b01011100 2
15
b01011111 7
b01011110 9
b01011100 :
b01011110 =
b01011011 >
b01011100 ?
1A
b01011110 C
b01011100 D
1H
b01011011 I
b01011110 J
b111111101 L
b000000011 M
b001011011 N
b001011110 O
#53500000
0)
0+
05
0A
#54000000
b01011100 !
1)
1+
b01011100 -
10
b01011111 1
b01011011 2
15
b01011100 7
b01011111 9
b01011011 :
b01011111 =
b01011110 >
b01011011 ?
1A
b01011111 C
b01011011 D
1H
b01011110 I
b01011100 J
b000000010 L
b000000010 M
b001011110 N
b001011100 O
#54500000
0)
0+
05
0A
#55000000
1)
1+
10
b01011100 1
b01011110 2
15
b01011100 9
b01011110 :
b01011100 =
b01011111 >
b01011110 ?
1A
b01011100 C
b01011110 D
1H
b01011111 I
b01011011 J
b000000100 L
b000000100 M
b001011111 N
b001011011 O
#55500000
0)
0+
05
0A
#56000000
1)
1+
10
b01011111 2
15
b01011111 :
b01011100 >
b01011111 ?
1A
b01011111 D
1H
b01011100 I
b01011110 J
b111111110 L
b000000010 M
b001011100 N
b001011110 O
#56500000
0)
0+
05
0A
#57000000
b01011101 !
1)
1+
b01011101 -
10
b01011100 2
15
b01011101 7
b01011100 :
b01011100 ?
1A
b01011100 D
1H
b01011111 J
b111111101 L
b000000011 M
b001011111 O
#57500000
0)
0+
05
0A
#58000000
b01011111 !
1)
1+
b01011111 -
10
b01011101 1
15
b01011111 7
b01011101 9
b01011101 =
1A
b01011101 C
1H
b01011100 J
b000000000 L
b000000000 M
b001011100 O
#58500000
0)
0+
05
0A
#59000000
b01011110 !
1)
1+
b01011110 -
10
b01011111 1
15
b01011110 7
b01011111 9
b01011111 =
b01011101 >
1A
b01011111 C
1H
b01011101 I
b000000001 L
b000000001 M
b001011101 N
#59500000
0)
0+
05
0A
#60000000
b01011111 !
1)
1+
b01011111 -
10
b01011110 1
b01011101 2
15
b01011111 7
b01011110 9
b01011101 :
b01011110 =
b01011111 >
b01011101 ?
1A
b01011110 C
b01011101 D
1H
b01011111 I
b000000011 L
b000000011 M
b001011111 N
#60500000
0)
0+
05
0A
#61000000
b01100000 !
1)
1+
b01100000 -
10
b01011111 1
b01011111 2
15
b01100000 7
b01011111 9
b01011111 :
b01011111 =
b01011110 >
b01011111 ?
1A
b01011111 C
b01011111 D
1H
b01011110 I
b01011101 J
b000000001 L
b000000001 M
b001011110 N
b001011101 O
#61500000
0)
0+
05
0A
#62000000
b01100010 !
1)
1+
b01100010 -
10
b01100000 1
b01011110 2
15
b01100010 7
b01100000 9
b01011110 :
b01100000 =
b01011111 >
b01011110 ?
1A
b01100000 C
b01011110 D
1H
b01011111 I
b01011111 J
b000000000 L
b000000000 M
b001011111 N
b001011111 O
#62500000
0)
0+
05
0A
#63000000
b01100001 !
1)
1+
b01100001 -
10
b01100010 1
b01011111 2
15
b01100001 7
b01100010 9
b01011111 :
b01100010 =
b01100000 >
b01011111 ?
1A
b01100010 C
b01011111 D
1H
b01100000 I
b01011110 J
b000000010 L
b000000010 M
b001100000 N
b001011110 O
#63500000
0)
0+
05
0A
#64000000
b01100000 !
1)
1+
b01100000 -
10
b01100001 1
b01100000 2
15
b01100000 7
b01100001 9
b01100000 :
b01100001 =
b01100010 >
b01100000 ?
1A
b01100001 C
b01100000 D
1H
b01100010 I
b01011111 J
b000000011 L
b000000011 M
b001100010 N
b001011111 O
#64500000
0)
0+
05
0A
#65000000
b01100011 !
1)
1+
b01100011 -
10
b01100000 1
b01100010 2
15
b01100011 7
b01100000 9
b01100010 :
b01100000 =
b01100001 >
b01100010 ?
1A
b01100000 C
b01100010 D
1H
b01100001 I
b01100000 J
b000000001 L
b000000001 M
b001100001 N
b001100000 O
#65500000
0)
0+
05
0A
#66000000
1)
1+
10
b01100011 1
b01100001 2
15
b01100011 9
b01100001 :
b01100011 =
b01100000 >
b01100001 ?
1A
b01100011 C
b01100001 D
1H
b01100000 I
b01100010 J
b111111110 L
b000000010 M
b001100000 N
b001100010 O
#66500000
0)
0+
05
0A
#67000000
b01011101 !
1)
1+
b01011101 -
10
b01100000 2
15
b01011101 7
b01100000 :
b01100011 >
b01100000 ?
1A
b01100000 D
1H
b01100011 I
b01100001 J
b000000010 L
b001100011 N
b001100001 O
#67500000
0)
0+
05
0A
#68000000
b01010100 !
1)
1+
b01010100 -
10
b01011101 1
b01100011 2
15
b01010100 7
b01011101 9
b01100011 :
b01011101 =
b01100011 ?
1A
b01011101 C
b01100011 D
1H
b01100000 J
b000000011 L
b000000011 M
b001100000 O
#68500000
0)
0+
05
0A
#69000000
b01001101 !
0#
1)
1+
b01001101 -
0/
10
b01010100 1
15
b01001101 7
b01010100 9
b01010100 =
b01011101 >
1A
b01010100 C
0G
1H
b01011101 I
b01100011 J
b111111010 L
b000000110 M
b001011101 N
b001100011 O
#69500000
b0 &
0)
0+
05
0A
#70000000
b01001001 !
b0 (
1)
1+
b01001001 -
10
b01001101 1
b01011101 2
15
b01001001 7
b01001101 9
b01011101 :
b01001101 =
b01010100 >
b01011101 ?
1A
b01001101 C
b01011101 D
1H
b01010100 I
b111110001 L
b000001111 M
b001010100 N
#70500000
0)
0+
05
0A
